Ejercicio 4/digito_Z.v
module digito_Z (
    input A, input B, input C, input D, output oZ
);
    assign oZ = ~D;

endmodule

Ejercicio 4/digito_Y.v
module digito_Y (
    input A, input B, input C, input D, output oY
);
    assign oY  = ~A & ~C & D | C & ~D;

endmodule

Ejercicio 4/digito_X.v
module digito_X (
    input A, input B, input C, input D, output oX
);
    assign oX = B & ~C | C & (B^D);

endmodule

Ejercicio 4/digito_W.v
module digito_W (
    input A, input B, input C, input D, output oW
);
    assign oW = B & C & D | A & ~C & ~D;
    
endmodule

Ejercicio 4/BCD.v
`include "digito_W.v"
`include "digito_X.v"
`include "digito_Y.v"
`include "digito_Z.v"

module BCD (
    input in_A, input in_B, input in_C, input in_D, output out_W, output out_X, output out_Y, output out_Z
);
    digito_W dW(.oW(out_W), .A(in_A), .B(in_B), .C(in_C), .D(in_D));
    digito_X dX(.oX(out_X), .A(in_A), .B(in_B), .C(in_C), .D(in_D));
    digito_Y dY(.oY(out_Y), .A(in_A), .B(in_B), .C(in_C), .D(in_D));
    digito_Z dZ(.oZ(out_Z), .A(in_A), .B(in_B), .C(in_C), .D(in_D)); //Podriamos utilizar solamente: not dZ(out_Z, D);

endmodule

Ejercicio 4/BCD_tb.v
`timescale 1ns/1ns
module BCD_tb;
    reg A, B, C, D;
    wire oW, oX, oY, oZ;
    
    BCD testBCD(.in_A(A), .in_B(B), .in_C(C), .in_D(D), .out_W(oW), .out_X(oX), .out_Y(oY), .out_Z(oZ));
    initial begin
        A=0;
        B=0;
        C=0;
        D=0;
        $display("ABCD: %b%b%b%b", A, B, C, D);
        #1
        $display("ABCD: %b%b%b%b -> WXYZ: %b%b%b%b", A, B, C, D, oW, oX, oY, oZ);
        #1    
        A=0;
        B=0;
        C=0;
        D=1;
        $display("ABCD: %b%b%b%b", A, B, C, D);
        #1
        $display("ABCD: %b%b%b%b -> WXYZ: %b%b%b%b", A, B, C, D, oW, oX, oY, oZ);
        #1    
        A=0;
        B=0;
        C=1;
        D=0;
        $display("ABCD: %b%b%b%b", A, B, C, D);
        #1
        $display("ABCD: %b%b%b%b -> WXYZ: %b%b%b%b", A, B, C, D, oW, oX, oY, oZ);
        #1    
        A=0;
        B=0;
        C=1;
        D=1;
        $display("ABCD: %b%b%b%b", A, B, C, D);
        #1
        $display("ABCD: %b%b%b%b -> WXYZ: %b%b%b%b", A, B, C, D, oW, oX, oY, oZ);
        #1    
        A=0;
        B=1;
        C=0;
        D=0;
        $display("ABCD: %b%b%b%b", A, B, C, D);
        #1
        $display("ABCD: %b%b%b%b -> WXYZ: %b%b%b%b", A, B, C, D, oW, oX, oY, oZ);
        #1    
        A=0;
        B=1;
        C=0;
        D=1;
        $display("ABCD: %b%b%b%b", A, B, C, D);
        #1
        $display("ABCD: %b%b%b%b -> WXYZ: %b%b%b%b", A, B, C, D, oW, oX, oY, oZ);
        #1    
        A=0;
        B=1;
        C=1;
        D=0;
        $display("ABCD: %b%b%b%b", A, B, C, D);
        #1
        $display("ABCD: %b%b%b%b -> WXYZ: %b%b%b%b", A, B, C, D, oW, oX, oY, oZ);
        #1    
        A=0;
        B=1;
        C=1;
        D=1;
        $display("ABCD: %b%b%b%b", A, B, C, D);
        #1
        $display("ABCD: %b%b%b%b -> WXYZ: %b%b%b%b", A, B, C, D, oW, oX, oY, oZ);
        #1
        A=1;
        B=0;
        C=0;
        D=0;
        $display("ABCD: %b%b%b%b", A, B, C, D);
        #1
        $display("ABCD: %b%b%b%b -> WXYZ: %b%b%b%b", A, B, C, D, oW, oX, oY, oZ);
        #1    
        A=1;
        B=0;
        C=0;
        D=1;
        $display("ABCD: %b%b%b%b", A, B, C, D);
        #1
        $display("ABCD: %b%b%b%b -> WXYZ: %b%b%b%b", A, B, C, D, oW, oX, oY, oZ);
    end
    initial begin
        $dumpfile("BCD.vcd");
        $dumpvars;
    end
endmodule

Ejercicio 4/ejercicio4_BCD.vcd
$date
	Tue Sep 21 22:55:35 2021
$end
$version
	Icarus Verilog
$end
$timescale
	1ns
$end
$scope module BCD_tb $end
$var wire 1 ! oZ $end
$var wire 1 " oY $end
$var wire 1 # oX $end
$var wire 1 $ oW $end
$var reg 1 % A $end
$var reg 1 & B $end
$var reg 1 ' C $end
$var reg 1 ( D $end
$scope module testBCD $end
$var wire 1 % in_A $end
$var wire 1 & in_B $end
$var wire 1 ' in_C $end
$var wire 1 ( in_D $end
$var wire 1 ! out_Z $end
$var wire 1 " out_Y $end
$var wire 1 # out_X $end
$var wire 1 $ out_W $end
$scope module dW $end
$var wire 1 % A $end
$var wire 1 & B $end
$var wire 1 ' C $end
$var wire 1 ( D $end
$var wire 1 $ oW $end
$upscope $end
$scope module dX $end
$var wire 1 % A $end
$var wire 1 & B $end
$var wire 1 ' C $end
$var wire 1 ( D $end
$var wire 1 # oX $end
$upscope $end
$scope module dY $end
$var wire 1 % A $end
$var wire 1 & B $end
$var wire 1 ' C $end
$var wire 1 ( D $end
$var wire 1 " oY $end
$upscope $end
$scope module dZ $end
$var wire 1 % A $end
$var wire 1 & B $end
$var wire 1 ' C $end
$var wire 1 ( D $end
$var wire 1 ! oZ $end
$upscope $end
$upscope $end
$upscope $end
$enddefinitions $end
#0
$dumpvars
0(
0'
0&
0%
0$
0#
0"
1!
$end
#2
1"
0!
1(
#4
0#
1!
0(
1'
#6
1#
0"
0!
1(
#8
1#
1!
0(
0'
1&
#10
1"
0!
1(
#12
1!
0(
1'
#14
0#
0"
1$
0!
1(
#16
1!
0(
0'
0&
1%
#18
0$
0!
1(
